[
  {
    "title": "CharGrinn",
    "description": "Visceral, Grim, & Simplistic.",
    "author": "NotSafeForAdults64",
    "maintainers": [
      "github/notsafeforadults64"
    ],
    "game": "skyrimspecialedition",
    "official": true,
    "tags": [
      "Performance",
      "Visceral",
      "Grim",
      "Vokriinator",
      "CGO",
      "Creation Club",
      "LotD"
    ],
    "nsfw": false,
    "utility_list": false,
    "image_contains_title": false,
    "force_down": false,
    "links": {
      "image": "https://github.com/notsafeadults64/CharGrinn_Modlist/blob/main/CharGrinn_GH01.png",
      "readme": "https://github.com/notsafeadults64/CharGrinn_Modlist/blob/main/README.md",
      "download": "https://authored-files.wabbajack.org/CharGrinn.wabbajack_d35809a3-1fff-4392-b6b6-a10419f4d199",
      "machineURL": "CharGrinn_Modlist/CharGrinn",
      "discordURL": ""
    },
    "download_metadata": {
      "Hash": "OjtXihsYETs=",
      "Size": 320893017,
      "NumberOfArchives": 1593,
      "SizeOfArchives": 135086896944,
      "NumberOfInstalledFiles": 281196,
      "SizeOfInstalledFiles": 268825259881
    }
    "version": "0.0.1.0",
    "dateCreated": "2023-03-18T04:15:15.0000000A",
    "dateUpdated": "2023-03-20T02:04:15.0000000P",
    "repositoryName": ""
  }
]
